posit2023_nbdev/__init__.py
posit2023_nbdev/_modidx.py
posit2023_nbdev/card.py
posit2023_nbdev/core.py
posit2023_nbdev/deck.py
posit2023_nbdev-0.0.1.dist-info/LICENSE
posit2023_nbdev-0.0.1.dist-info/METADATA
posit2023_nbdev-0.0.1.dist-info/WHEEL
posit2023_nbdev-0.0.1.dist-info/entry_points.txt
posit2023_nbdev-0.0.1.dist-info/top_level.txt
posit2023_nbdev-0.0.1.dist-info/RECORD
